ALU.v


module ALU (
    input   wire            i_clk,
    input   wire    [31:0]  i_input_a,
    input   wire    [31:0]  i_input_b,
    input   wire    [3:0]   i_alu_op,
    output  reg     [31:0]  o_result,
    output  reg             o_zero
);
    initial begin
        o_result = 32'h00000000;
        o_zero = 1'b0;
    end
    
    always @(posedge i_clk) begin
        case(i_alu_op[3:0])
            // ADD
            4'b0000: o_result <= i_input_a + i_input_b ;
            // SLL
            4'b0001: o_result <= i_input_a << i_input_b[4:0];
            // SLT
            4'b0010: o_result <= $signed(i_input_a) < $signed(i_input_b) ? 1 : 0;
            // SLTU
            4'b0011: o_result <= i_input_a < i_input_b ? 1 : 0;
            // XOR
            4'b0100: o_result <= i_input_a ^ i_input_b;
            // SRL
            4'b0101: o_result <= i_input_a >> i_input_b[4:0];
            // OR
            4'b0110: o_result <= i_input_a | i_input_b;
            // AND
            4'b0111: o_result <= i_input_a & i_input_b;
            // SUB
            4'b1000: o_result <= i_input_a - i_input_b ;
            // SRA
            4'b1101: o_result <= $signed(i_input_a) >>> i_input_b[4:0];
            // BNE
            4'b1111: o_result <= i_input_a != i_input_b ? 0 : 1;
            // BLT
            4'b1100: o_result <= $signed(i_input_a) < $signed(i_input_b) ? 0 : 1;
            // BGE
            4'b1011: o_result <= $signed(i_input_a) >= $signed(i_input_b) ? 0 : 1;
            // BLTU
            4'b1010: o_result <= i_input_a < i_input_b ? 0 : 1;
            // BGEU
            4'b1001: o_result <= i_input_a >= i_input_b ? 0 : 1;
            default: o_result <= 32'h00000000;
        endcase
        o_zero <= o_result == 32'h00000000;
    end

endmodule

ALU_tb.v
module alu_tb;
    reg             clk         = 1'b0;
    reg     [31:0]  input_a     = 32'h00000000;
    reg     [31:0]  input_b     = 32'h00000000;
    reg     [3:0]   opcode      = 4'b0000;
    wire    [31:0]  out;
    wire            zero;


    initial begin
        $dumpfile("ALU.vcd");
        $dumpvars(0, DUT);
    end

    always #1 begin
        clk <= ~clk;
    end


    ALU DUT (
        .i_clk      (clk),
        .i_input_a  (input_a),
        .i_input_b  (input_b),
        .i_alu_op   (opcode),
        .o_result   (out),
        .o_zero     (zero)
    );

    initial begin
        // ADD
        input_a = 32'h0000adde;
        input_b = 32'hefbe0000;
        opcode  = 4'b0000;
        #2
        // SLL
        input_a = 32'h0000ffff;
        input_b = 32'hffffff0c;
        opcode = 4'b0001;
        #2
        // SLT
        input_a = 32'hfffc0000;
        input_b = 32'h7fffffff;
        opcode = 4'b0010;
        #2
        // SLTU
        input_a = 32'hfffc0000;
        input_b = 32'h7fffffff;
        opcode = 4'b0011;
        #2
        // XOR
        input_a = 32'h5555aaaa;
        input_b = 32'haaaaffff;
        opcode = 4'b0100;
        #2
        // SRL
        input_a = 32'hffff0000;
        input_b = 32'hffffff0c;
        opcode = 4'b0101;
        #2
        // OR
        input_a = 32'h5555001c;
        input_b = 32'haaaa007f;
        opcode = 4'b0110;
        #2
        // AND
        input_a = 32'h5555001c;
        input_b = 32'haaaa007f;
        opcode = 4'b0111;
        #2
        // SUB
        input_a = 32'haaaa007f;
        input_b = 32'h5555001c;
        opcode = 4'b1000;
        #2
        // SRA
        input_a = 32'hffff0000;
        input_b = 32'hffffff0c;
        opcode = 4'b1101;
        #2
        #1
        $finish;
    end


endmodule

ALU.vcd
$date
	Wed Oct  2 14:11:05 2024
$end
$version
	Icarus Verilog
$end
$timescale
	1s
$end
$scope module alu_tb $end
$scope module DUT $end
$var wire 4 ! i_alu_op [3:0] $end
$var wire 1 " i_clk $end
$var wire 32 # i_input_a [31:0] $end
$var wire 32 $ i_input_b [31:0] $end
$var reg 32 % o_result [31:0] $end
$var reg 1 & o_zero $end
$upscope $end
$upscope $end
$enddefinitions $end
$comment Show the parameter values. $end
$dumpall
$end
#0
$dumpvars
x&
b0 %
b11101111101111100000000000000000 $
b1010110111011110 #
0"
b0 !
$end
#1
1&
b11101111101111101010110111011110 %
1"
#2
0"
b1 !
b11111111111111111111111100001100 $
b1111111111111111 #
#3
0&
b1111111111111111000000000000 %
1"
#4
0"
b10 !
b1111111111111111111111111111111 $
b11111111111111000000000000000000 #
#5
b1 %
1"
#6
0"
b11 !
#7
b0 %
1"
#8
0"
b100 !
b10101010101010101111111111111111 $
b1010101010101011010101010101010 #
#9
1&
b11111111111111110101010101010101 %
1"
#10
0"
b101 !
b11111111111111111111111100001100 $
b11111111111111110000000000000000 #
#11
0&
b11111111111111110000 %
1"
#12
0"
b110 !
b10101010101010100000000001111111 $
b1010101010101010000000000011100 #
#13
b11111111111111110000000001111111 %
1"
#14
0"
b111 !
#15
b11100 %
1"
#16
0"
b1000 !
b1010101010101010000000000011100 $
b10101010101010100000000001111111 #
#17
b1010101010101010000000001100011 %
1"
#18
0"
b1101 !
b11111111111111111111111100001100 $
b11111111111111110000000000000000 #
#19
b11111111111111111111111111110000 %
1"
