ALU.v


module ALU (
    input   wire            i_clk,
    input   wire    [31:0]  i_input_a,
    input   wire    [31:0]  i_input_b,
    input   wire    [3:0]   i_alu_op,
    output  reg     [31:0]  o_result,
    output  wire            o_zero
);
    initial begin
        o_result = 32'h00000000;
    end
    
    always @(*) begin
        case(i_alu_op[3:0])
            // ADD
            4'b0000: o_result <= i_input_a + i_input_b ;
            // SLL
            4'b0001: o_result <= i_input_a << i_input_b[4:0];
            // SLT
            4'b0010: o_result <= $signed(i_input_a) < $signed(i_input_b) ? 1 : 0;
            // SLTU
            4'b0011: o_result <= i_input_a < i_input_b ? 1 : 0;
            // XOR
            4'b0100: o_result <= i_input_a ^ i_input_b;
            // SRL
            4'b0101: o_result <= i_input_a >> i_input_b[4:0];
            // OR
            4'b0110: o_result <= i_input_a | i_input_b;
            // AND
            4'b0111: o_result <= i_input_a & i_input_b;
            // SUB
            4'b1000: o_result <= i_input_a - i_input_b ;
            // SRA
            4'b1101: o_result <= $signed(i_input_a) >>> i_input_b[4:0];
            // BNE
            4'b1111: o_result <= i_input_a != i_input_b ? 0 : 1;
            // BLT
            4'b1100: o_result <= $signed(i_input_a) < $signed(i_input_b) ? 0 : 1;
            // BGE
            4'b1011: o_result <= $signed(i_input_a) >= $signed(i_input_b) ? 0 : 1;
            // BLTU
            4'b1010: o_result <= i_input_a < i_input_b ? 0 : 1;
            // BGEU
            4'b1001: o_result <= i_input_a >= i_input_b ? 0 : 1;
            default: o_result <= 32'h00000000;
        endcase
    end

    assign o_zero = o_result == 32'h00000000;


endmodule

Decoder.v



module Decoder (
    input   wire    [31:0]  i_opcode,
    input   wire    [31:0]  i_pc,
    output  reg     [4:0]   o_rd,
    output  reg     [4:0]   o_rs1,
    output  reg     [4:0]   o_rs2,
    output  reg             o_en_imm,
    output  reg     [31:0]  o_imm,
    output  reg             o_en_jump,
    output  reg     [31:0]  o_jump_addr,
    output  reg     [3:0]   o_alu_op,
    output  reg     [1:0]   o_jump,
    output  reg             o_illegal_instruction
);
    wire    [6:0]   opcode;
    wire    [4:0]   rd;
    wire    [2:0]   funct3;
    wire    [4:0]   rs1;
    wire    [4:0]   rs2;
    wire    [6:0]   funct7;
    wire    [31:0]  I_immediate;
    wire    [31:0]  U_immediate;
    wire    [31:0]  J_immediate;
    wire    [31:0]  B_immediate;
    wire    [31:0]  S_immediate;
    
    

    initial begin
        o_rd                    = 0;
        o_rs1                   = 0;
        o_rs2                   = 0;
        o_en_imm                = 0;
        o_imm                   = 0;
        o_en_jump               = 0;
        o_jump_addr             = 0;
        o_alu_op                = 0;
        o_jump                  = 0;
        o_illegal_instruction   = 1;
    end

    assign opcode       = i_opcode[6:0];
    assign rd           = i_opcode[11:7];
    assign funct3       = i_opcode[14:12];
    assign rs1          = i_opcode[19:15];
    assign rs2          = i_opcode[24:20];
    assign funct7       = i_opcode[31:25];
    assign I_immediate  = i_opcode[31] ? {{20{1'b1}},i_opcode[31:20]} : {{20{1'b0}},i_opcode[31:20]};
    assign U_immediate  = {i_opcode[31:12],{12{1'b0}}};
    assign J_immediate  = i_opcode[31] ? {{12{1'b1}},i_opcode[19:12],i_opcode[20],i_opcode[30:25],i_opcode[24:21],1'b0}
                                       : {{12{1'b0}},i_opcode[19:12],i_opcode[20],i_opcode[30:25],i_opcode[24:21],1'b0};
    assign B_immediate  = i_opcode[31] ? {{20{1'b1}},i_opcode[7],i_opcode[30:25],i_opcode[11:8],1'b0}
                                       : {{20{1'b0}},i_opcode[7],i_opcode[30:25],i_opcode[11:8],1'b0};
    assign S_immediate  = i_opcode[31] ? {{20{1'b1}},i_opcode[31:25],i_opcode[11:8],i_opcode[7]}
                                       : {{20{1'b0}},i_opcode[31:25],i_opcode[11:8],i_opcode[7]};

    parameter opcode_OP         = 7'b0110011;
    parameter opcode_OP_IMM     = 7'b0010011;
    parameter opcode_SYSTEM     = 7'b1110011;
    parameter opcode_AUIPC      = 7'b0010111;
    parameter opcode_LUI        = 7'b0110111;
    parameter opcode_JAL        = 7'b1101111;
    parameter opcode_JALR       = 7'b1100111;
    parameter opcode_BRANCH     = 7'b1100011;
    parameter opcode_LOAD       = 7'b0000011;
    parameter opcode_STORE      = 7'b0100011;

    always @(*) begin
        case(opcode)
            opcode_OP: begin
                o_rd                    <= rd;
                o_rs1                   <= rs1;
                o_rs2                   <= rs2;
                o_en_imm                <= 0;
                o_alu_op                <= {funct7[5],funct3};
                o_en_jump               <= 0;
                o_jump                  <= 0;
                o_illegal_instruction   <= 0;
            end
            opcode_OP_IMM: begin
                o_rd                    <= rd;
                o_rs1                   <= rs1;
                o_rs2                   <= 0;
                o_en_imm                <= 1;
                o_imm                   <= (funct3 == 3'b001 || funct3 == 3'b101) ? 
                                           {{27{1'b0}},rs2} :                                     // for shift 
                                           I_immediate;
                o_alu_op                <= (funct3 == 3'b001 || funct3 == 3'b101) ? 
                                           {funct7[5],funct3} :                                   // for shift
                                           funct3;
                o_en_jump               <= 0;
                o_jump                  <= 0;
                o_illegal_instruction   <= 0;
            end
            opcode_AUIPC: begin
                o_rd                    <= rd;
                o_rs1                   <= 0;
                o_rs2                   <= 0;
                o_en_imm                <= 1;
                o_imm                   <= U_immediate;
                o_en_jump               <= 1;
                o_jump_addr             <= i_pc;
                o_alu_op                <= 4'b0000; // add
                o_jump                  <= 0;
                o_illegal_instruction   <= 0;
            end
            opcode_LUI: begin
                o_rd                    <= rd;
                o_rs1                   <= 0;
                o_rs2                   <= 0;
                o_en_imm                <= 1;
                o_imm                   <= U_immediate;
                o_en_jump               <= 0;
                o_jump_addr             <= 0;
                o_alu_op                <= 4'b0000; // add
                o_jump                  <= 0;
                o_illegal_instruction   <= 0;
            end
            opcode_JAL: begin
                o_rd                    <= rd;
                o_rs1                   <= 0;
                o_rs2                   <= 0;
                o_en_imm                <= 1;
                o_imm                   <= i_pc + 4;
                o_en_jump               <= 1;
                o_jump_addr             <= i_pc + J_immediate;
                o_alu_op                <= 4'b0000; // add
                o_jump                  <= 1;
                o_illegal_instruction   <= 0;
            end
            opcode_JALR: begin
                o_rd                    <= rd;
                o_rs1                   <= rs1;
                o_rs2                   <= 0;
                o_en_imm                <= 1;
                o_imm                   <= I_immediate;
                o_en_jump               <= 1;
                o_jump_addr             <= i_pc + 4;
                o_alu_op                <= 4'b0000; // add
                o_jump                  <= 2;
                o_illegal_instruction   <= 0;
            end
            opcode_BRANCH: begin
                o_rd                    <= 0;
                o_rs1                   <= rs1;
                o_rs2                   <= rs2;
                o_en_imm                <= 0;
                o_alu_op                <= {1'b1,-funct3};
                o_en_jump               <= 1;
                o_jump_addr             <= i_pc + B_immediate;
                o_jump                  <= 3;
                o_illegal_instruction   <= 0;
            end
            default: begin
                o_rd                    <= 0;
                o_rs1                   <= 0;
                o_rs2                   <= 0;
                o_en_imm                <= 0;
                o_illegal_instruction   <= 1;
            end
        endcase
    end

endmodule

RegFile.v
module RegFile (
    input   wire            i_clk,
    input   wire    [31:0]  i_wdata,
    input   wire    [4:0]   i_waddr,
    output  wire    [31:0]  o_r1data,
    input   wire    [4:0]   i_r1addr,
    output  wire    [31:0]  o_r2data,
    input   wire    [4:0]   i_r2addr
);

    reg [31:0] register [31:0];

    integer i;

    initial begin
        for (i = 0; i < 32; i = i + 1) begin
            register[i] = 32'h00000000;
        end
    end

    always @(posedge i_clk) begin
        register[i_waddr] <= i_wdata;
    end

    assign o_r1data = i_r1addr == 5'b00000 ? 32'h00000000 : register[i_r1addr];
    assign o_r2data = i_r2addr == 5'b00000 ? 32'h00000000 : register[i_r2addr];


endmodule

CPU.v
`include "ALU.v"
`include "Decoder.v"
`include "RegFile.v"


module cpu (
    input   wire            i_clk,
    input   wire            i_nreset,
    input   wire    [31:0]  i_membus,
    output  reg             o_memwrite,
    output  reg             o_memread,
    output  reg     [31:0]  o_memaddr
);
    reg     [31:0]  pc = 32'h80000000;    

    reg     [31:0]  insn = 32'h00000000;
    wire    [4:0]   rd;
    wire    [4:0]   rs1;
    wire    [31:0]  rs1data;
    wire    [4:0]   rs2;
    wire    [31:0]  rs2data;
    wire            en_imm;
    wire    [31:0]  imm;
    wire            en_jump;
    wire    [31:0]  jump_addr;
    wire    [3:0]   alu_op;
    wire    [1:0]   jump;
    wire            illegal_instruction;
    wire    [31:0]  alu_result;
    reg     [31:0]  reg_wdata   = 32'h00000000;
    wire    [31:0]  alu_input_a;
    wire    [31:0]  alu_input_b;
    wire            cond;
    reg             fetch = 1'b1;

    initial begin
        o_memwrite = 1'b0;
        o_memread  = 1'b1;
        o_memaddr  = 32'h00000000;
    end

    assign alu_input_a = rs1data;
    assign alu_input_b = en_imm ? imm : rs2data;

    RegFile reg_file (
        .i_clk      (i_clk),
        .i_wdata    (reg_wdata),
        .i_waddr    (rd),
        .o_r1data   (rs1data),
        .i_r1addr   (rs1),
        .o_r2data   (rs2data),
        .i_r2addr   (rs2)
    );

    Decoder decoder (
        .i_opcode               (insn),
        .i_pc                   (pc),
        .o_rd                   (rd),
        .o_rs1                  (rs1),
        .o_rs2                  (rs2),
        .o_en_imm               (en_imm),
        .o_imm                  (imm),
        .o_en_jump              (en_jump),
        .o_jump_addr            (jump_addr),
        .o_alu_op               (alu_op),
        .o_jump                 (jump),
        .o_illegal_instruction  (illegal_instruction)
    );

    ALU alu (
        .i_clk      (i_clk),
        .i_alu_op   (alu_op),
        .i_input_a  (rs1data),
        .i_input_b  (alu_input_b),
        .o_result   (alu_result),
        .o_zero     (cond)
    );

    always @(*) begin
        o_memaddr = fetch ? pc : 32'h00000000;
    end

    always @(posedge i_clk) begin
        if (!i_nreset) begin
            pc <= 32'h80000000;
        end
        else begin
            insn <= i_membus;
        end
    end

    always @(negedge i_clk) begin
        if (!i_nreset) begin
            pc <= 32'h80000000;
        end
        else begin
            case (jump)
                2'b00: begin
                    reg_wdata <= alu_result;        // no jump
                    pc        <= pc + 4;
                end
                2'b01: begin
                    reg_wdata <= alu_result;        // jal
                    pc        <= jump_addr;
                end
                2'b10: begin
                    reg_wdata <= jump_addr;         // jalr
                    pc        <= alu_result;
                end
                2'b11: begin
                    reg_wdata <= alu_result;        // branch
                    if (cond) begin
                        pc <= jump_addr;
                    end else begin
                        pc <= pc + 4;
                    end
                end
            endcase
        end
    end

    /*
    always @(posedge i_clk or negedge i_nreset) begin
        if (!i_nreset) begin
            pc <= 32'h80000000;
        end
        else begin
            case (jump)
                2'b00: begin
                    reg_wdata <= alu_result;        // no jump
                    pc        <= pc + 4;
                end
                2'b01: begin
                    reg_wdata <= alu_result;        // jal
                    pc        <= jump_addr;
                end
                2'b10: begin
                    reg_wdata <= jump_addr;         // jalr
                    pc        <= alu_result;
                end
                2'b11: begin
                    reg_wdata <= alu_result;        // branch
                    if (cond) begin
                        pc <= jump_addr;
                    end else begin
                        pc <= pc + 4;
                    end
                end
            endcase
            o_memaddr = pc;
            insn      = i_membus;
        end
    end
    */


endmodule

CPU_tb.v
module Memory (
    input   wire            i_clk,
    input   wire            i_memread,
    input   wire    [31:0]  i_memaddr,
    output  reg     [31:0]  o_membus
);

    reg [31:0] memory [0:255];
    wire [31:0] addr;

    initial begin
        $readmemh("test.hex", memory);
    end

    always @(*) begin
        o_membus = memory[addr];
    end


    assign addr = (32'h80000000 <= i_memaddr && i_memaddr <= 32'h800003fc) ? (i_memaddr - 32'h80000000) >> 2 : 32'h00000000;
                                 

endmodule



module CPU_tb;
    reg             clk = 1'b0;
    wire            memwrite = 1'b0;
    wire            memread = 1'b1;
    wire    [31:0]  memaddr;
    wire    [31:0]  membus;
    reg             nreset = 1'b0;

    Memory mem (
        .i_clk      (clk),
        .i_memread  (memread),
        .i_memaddr  (memaddr),
        .o_membus   (membus)
    );

    cpu DUT (
        .i_clk      (clk),
        .i_nreset   (nreset),
        .o_memaddr  (memaddr),
        .o_memwrite (memwrite),
        .o_memread  (memread),
        .i_membus   (membus)
    );


    initial begin
        $dumpfile("CPU.vcd");
        $dumpvars(0);
    end

    always #1 begin
        clk = ~clk;
    end


    initial begin
        #2
        nreset = 1'b1;
        #160
        $finish;
    end


endmodule

CPU.vcd
$date
	Thu Oct  3 06:55:48 2024
$end
$version
	Icarus Verilog
$end
$timescale
	1s
$end
$scope module CPU_tb $end
$var wire 1 ! memread $end
$var wire 1 " memwrite $end
$var wire 32 # membus [31:0] $end
$var wire 32 $ memaddr [31:0] $end
$var reg 1 % clk $end
$var reg 1 & nreset $end
$scope module DUT $end
$var wire 32 ' alu_input_a [31:0] $end
$var wire 1 % i_clk $end
$var wire 1 & i_nreset $end
$var wire 32 ( rs2data [31:0] $end
$var wire 5 ) rs2 [4:0] $end
$var wire 32 * rs1data [31:0] $end
$var wire 5 + rs1 [4:0] $end
$var wire 5 , rd [4:0] $end
$var wire 32 - jump_addr [31:0] $end
$var wire 2 . jump [1:0] $end
$var wire 32 / imm [31:0] $end
$var wire 1 0 illegal_instruction $end
$var wire 32 1 i_membus [31:0] $end
$var wire 1 2 en_jump $end
$var wire 1 3 en_imm $end
$var wire 1 4 cond $end
$var wire 32 5 alu_result [31:0] $end
$var wire 4 6 alu_op [3:0] $end
$var wire 32 7 alu_input_b [31:0] $end
$var reg 1 8 fetch $end
$var reg 32 9 insn [31:0] $end
$var reg 32 : o_memaddr [31:0] $end
$var reg 1 ; o_memread $end
$var reg 1 < o_memwrite $end
$var reg 32 = pc [31:0] $end
$var reg 32 > reg_wdata [31:0] $end
$scope module alu $end
$var wire 1 % i_clk $end
$var wire 32 ? i_input_b [31:0] $end
$var wire 1 4 o_zero $end
$var wire 32 @ i_input_a [31:0] $end
$var wire 4 A i_alu_op [3:0] $end
$var reg 32 B o_result [31:0] $end
$upscope $end
$scope module decoder $end
$var wire 32 C i_opcode [31:0] $end
$var wire 32 D i_pc [31:0] $end
$var wire 5 E rs2 [4:0] $end
$var wire 5 F rs1 [4:0] $end
$var wire 5 G rd [4:0] $end
$var wire 7 H opcode [6:0] $end
$var wire 7 I funct7 [6:0] $end
$var wire 3 J funct3 [2:0] $end
$var wire 32 K U_immediate [31:0] $end
$var wire 32 L S_immediate [31:0] $end
$var wire 32 M J_immediate [31:0] $end
$var wire 32 N I_immediate [31:0] $end
$var wire 32 O B_immediate [31:0] $end
$var parameter 7 P opcode_AUIPC $end
$var parameter 7 Q opcode_BRANCH $end
$var parameter 7 R opcode_JAL $end
$var parameter 7 S opcode_JALR $end
$var parameter 7 T opcode_LOAD $end
$var parameter 7 U opcode_LUI $end
$var parameter 7 V opcode_OP $end
$var parameter 7 W opcode_OP_IMM $end
$var parameter 7 X opcode_STORE $end
$var parameter 7 Y opcode_SYSTEM $end
$var reg 4 Z o_alu_op [3:0] $end
$var reg 1 3 o_en_imm $end
$var reg 1 2 o_en_jump $end
$var reg 1 0 o_illegal_instruction $end
$var reg 32 [ o_imm [31:0] $end
$var reg 2 \ o_jump [1:0] $end
$var reg 32 ] o_jump_addr [31:0] $end
$var reg 5 ^ o_rd [4:0] $end
$var reg 5 _ o_rs1 [4:0] $end
$var reg 5 ` o_rs2 [4:0] $end
$upscope $end
$scope module reg_file $end
$var wire 1 % i_clk $end
$var wire 5 a i_r1addr [4:0] $end
$var wire 5 b i_r2addr [4:0] $end
$var wire 5 c i_waddr [4:0] $end
$var wire 32 d i_wdata [31:0] $end
$var wire 32 e o_r2data [31:0] $end
$var wire 32 f o_r1data [31:0] $end
$var integer 32 g i [31:0] $end
$upscope $end
$upscope $end
$scope module mem $end
$var wire 1 % i_clk $end
$var wire 32 h i_memaddr [31:0] $end
$var wire 1 ! i_memread $end
$var wire 32 i addr [31:0] $end
$var reg 32 j o_membus [31:0] $end
$upscope $end
$upscope $end
$enddefinitions $end
$comment Show the parameter values. $end
$dumpall
b1110011 Y
b100011 X
b10011 W
b110011 V
b110111 U
b11 T
b1100111 S
b1101111 R
b1100011 Q
b10111 P
$end
#0
$dumpvars
b10010001101000101000010110111 j
b0 i
b10000000000000000000000000000000 h
b100000 g
b0 f
b0 e
b0 d
b0 c
b0 b
b0 a
b0 `
b0 _
b0 ^
b0 ]
b0 \
b0 [
b0 Z
b0 O
b0 N
b0 M
b0 L
b0 K
b0 J
b0 I
b0 H
b0 G
b0 F
b0 E
b10000000000000000000000000000000 D
b0 C
b0 B
b0 A
b0 @
b0 ?
b0 >
b10000000000000000000000000000000 =
0<
1;
b10000000000000000000000000000000 :
b0 9
18
b0 7
b0 6
b0 5
14
03
02
b10010001101000101000010110111 1
10
b0 /
b0 .
b0 -
b0 ,
b0 +
b0 *
b0 )
b0 (
b0 '
0&
0%
b10000000000000000000000000000000 $
b10010001101000101000010110111 #
0"
1!
$end
#1
1%
#2
b1100111100000001000000010010011 #
b1100111100000001000000010010011 1
b1100111100000001000000010010011 j
b1 i
b10000000000000000000000000000100 $
b10000000000000000000000000000100 :
b10000000000000000000000000000100 h
b10000000000000000000000000000100 =
b10000000000000000000000000000100 D
0%
1&
#3
04
b11001111000 5
b11001111000 B
b11001111000 7
b11001111000 ?
b11001111000 /
b11001111000 [
00
13
b1 +
b1 _
b1 a
b1 ,
b1 ^
b1 c
b11001111000 N
b1000011001111000 M
b111001100000 O
b11001100001 L
b10011 H
b1 G
b1 F
b11000 E
b110011 I
b1100111100000001000000000000000 K
b1100111100000001000000010010011 9
b1100111100000001000000010010011 C
1%
#4
b100000000000100010011 #
b100000000000100010011 1
b100000000000100010011 j
b10 i
b10000000000000000000000000001000 $
b10000000000000000000000000001000 :
b10000000000000000000000000001000 h
b10000000000000000000000000001000 =
b10000000000000000000000000001000 D
b11001111000 >
b11001111000 d
0%
#5
b1 7
b1 ?
b1 /
b1 [
b1 5
b1 B
b0 +
b0 _
b0 a
b10 ,
b10 ^
b10 c
b1 N
b100000000000 M
b10 O
b10 L
b0 '
b0 *
b0 @
b0 f
b10 G
b0 F
b1 E
b0 I
b100000000000000000000 K
b100000000000100010011 9
b100000000000100010011 C
1%
#6
b1000000000000000110010011 #
b1000000000000000110010011 1
b1000000000000000110010011 j
b11 i
b10000000000000000000000000001100 $
b10000000000000000000000000001100 :
b10000000000000000000000000001100 h
b10000000000000000000000000001100 =
b10000000000000000000000000001100 D
b1 >
b1 d
0%
#7
b10000 5
b10000 B
b10000 7
b10000 ?
b10000 /
b10000 [
b11 ,
b11 ^
b11 c
b10000 N
b10000 M
b100000000010 O
b11 L
b11 G
b10000 E
b1000000000000000000000000 K
b1000000000000000110010011 9
b1000000000000000110010011 C
1%
#8
b1000110011 #
b1000110011 1
b1000110011 j
b100 i
b10000000000000000000000000010000 $
b10000000000000000000000000010000 :
b10000000000000000000000000010000 h
b10000000000000000000000000010000 =
b10000000000000000000000000010000 D
b10000 >
b10000 d
0%
#9
14
b0 5
b0 B
b0 7
b0 ?
03
b100 ,
b100 ^
b100 c
b0 N
b0 M
b100 O
b100 L
b110011 H
b100 G
b0 E
b0 K
b1000110011 9
b1000110011 C
1%
#10
b1100010000100001100011 #
b1100010000100001100011 1
b1100010000100001100011 j
b101 i
b10000000000000000000000000010100 $
b10000000000000000000000000010100 :
b10000000000000000000000000010100 h
b10000000000000000000000000010100 =
b10000000000000000000000000010100 D
b0 >
b0 d
0%
#11
04
b11111111111111111111111111110001 5
b11111111111111111111111111110001 B
b10000 7
b10000 ?
b10000 (
b10000 e
b1 '
b1 *
b1 @
b1 f
b11 .
b11 \
b10000000000000000000000000100100 -
b10000000000000000000000000100100 ]
12
b1000 6
b1000 A
b1000 Z
b11 )
b11 `
b11 b
b10 +
b10 _
b10 a
b0 ,
b0 ^
b0 c
b11 N
b10000100000000010 M
b10000 O
b10000 L
b1100011 H
b10000 G
b10 F
b11 E
b1100010000000000000000 K
b1100010000100001100011 9
b1100010000100001100011 C
1%
#12
b10000000000000000000000000101000 -
b10000000000000000000000000101000 ]
b1000100000001000110011 #
b1000100000001000110011 1
b1000100000001000110011 j
b110 i
b10000000000000000000000000011000 $
b10000000000000000000000000011000 :
b10000000000000000000000000011000 h
b10000000000000000000000000011000 =
b10000000000000000000000000011000 D
b11111111111111111111111111110001 >
b11111111111111111111111111110001 d
0%
#13
b1 5
b1 B
b1 7
b1 ?
b1 (
b1 e
b0 '
b0 *
b0 @
b0 f
b0 .
b0 \
02
b0 6
b0 A
b0 Z
b10 )
b10 `
b10 b
b100 +
b100 _
b100 a
b100 ,
b100 ^
b100 c
b10 N
b100000000000000010 M
b100 O
b100 L
b110011 H
b100 G
b100 F
b10 E
b1000100000000000000000 K
b1000100000001000110011 9
b1000100000001000110011 C
1%
#14
b100010000000100010011 #
b100010000000100010011 1
b100010000000100010011 j
b111 i
b10000000000000000000000000011100 $
b10000000000000000000000000011100 :
b10000000000000000000000000011100 h
b10000000000000000000000000011100 =
b10000000000000000000000000011100 D
b1 >
b1 d
0%
#15
b0 (
b0 e
b1 /
b1 [
13
b0 )
b0 `
b0 b
b10 +
b10 _
b10 a
b10 ,
b10 ^
b10 c
b10 5
b10 B
b1 N
b10000100000000000 M
b10 O
b10 L
b10011 H
b10 G
b10 F
b1 E
b100010000000000000000 K
b1 '
b1 *
b1 @
b1 f
b100010000000100010011 9
b100010000000100010011 C
1%
#16
b11111110000000000000101011100011 #
b11111110000000000000101011100011 1
b11111110000000000000101011100011 j
b1000 i
b10000000000000000000000000100000 $
b10000000000000000000000000100000 :
b10000000000000000000000000100000 h
b10000000000000000000000000100000 =
b10000000000000000000000000100000 D
b10 >
b10 d
0%
#17
14
b0 7
b0 ?
b0 5
b0 B
b11 .
b11 \
b10000000000000000000000000010100 -
b10000000000000000000000000010100 ]
12
b1000 6
b1000 A
b1000 Z
03
b0 +
b0 _
b0 a
b0 ,
b0 ^
b0 c
b11111111111111111111111111100000 N
b11111111111100000000011111100000 M
b11111111111111111111111111110100 O
b11111111111111111111111111110101 L
b0 '
b0 *
b0 @
b0 f
b1100011 H
b10101 G
b0 F
b0 E
b1111111 I
b11111110000000000000000000000000 K
b11111110000000000000101011100011 9
b11111110000000000000101011100011 C
1%
#18
b10000000000000000000000000001000 -
b10000000000000000000000000001000 ]
b1100010000100001100011 #
b1100010000100001100011 1
b1100010000100001100011 j
b101 i
b10000000000000000000000000010100 $
b10000000000000000000000000010100 :
b10000000000000000000000000010100 h
b10000000000000000000000000010100 =
b10000000000000000000000000010100 D
b0 >
b0 d
0%
#19
04
b11111111111111111111111111110010 5
b11111111111111111111111111110010 B
b10000 7
b10000 ?
b10000 (
b10000 e
b10 '
b10 *
b10 @
b10 f
b10000000000000000000000000100100 -
b10000000000000000000000000100100 ]
b11 )
b11 `
b11 b
b10 +
b10 _
b10 a
b11 N
b10000100000000010 M
b10000 O
b10000 L
b10000 G
b10 F
b11 E
b0 I
b1100010000000000000000 K
b1100010000100001100011 9
b1100010000100001100011 C
1%
#20
b10000000000000000000000000101000 -
b10000000000000000000000000101000 ]
b1000100000001000110011 #
b1000100000001000110011 1
b1000100000001000110011 j
b110 i
b10000000000000000000000000011000 $
b10000000000000000000000000011000 :
b10000000000000000000000000011000 h
b10000000000000000000000000011000 =
b10000000000000000000000000011000 D
b11111111111111111111111111110010 >
b11111111111111111111111111110010 d
0%
#21
b11 5
b11 B
b10 7
b10 ?
b10 (
b10 e
b1 '
b1 *
b1 @
b1 f
b0 .
b0 \
02
b0 6
b0 A
b0 Z
b10 )
b10 `
b10 b
b100 +
b100 _
b100 a
b100 ,
b100 ^
b100 c
b10 N
b100000000000000010 M
b100 O
b100 L
b110011 H
b100 G
b100 F
b10 E
b1000100000000000000000 K
b1000100000001000110011 9
b1000100000001000110011 C
1%
#22
b100010000000100010011 #
b100010000000100010011 1
b100010000000100010011 j
b111 i
b10000000000000000000000000011100 $
b10000000000000000000000000011100 :
b10000000000000000000000000011100 h
b10000000000000000000000000011100 =
b10000000000000000000000000011100 D
b11 >
b11 d
0%
#23
b1 7
b1 ?
b0 (
b0 e
b1 /
b1 [
13
b0 )
b0 `
b0 b
b10 +
b10 _
b10 a
b10 ,
b10 ^
b10 c
b11 5
b11 B
b1 N
b10000100000000000 M
b10 O
b10 L
b10011 H
b10 G
b10 F
b1 E
b100010000000000000000 K
b10 '
b10 *
b10 @
b10 f
b100010000000100010011 9
b100010000000100010011 C
1%
#24
b11111110000000000000101011100011 #
b11111110000000000000101011100011 1
b11111110000000000000101011100011 j
b1000 i
b10000000000000000000000000100000 $
b10000000000000000000000000100000 :
b10000000000000000000000000100000 h
b10000000000000000000000000100000 =
b10000000000000000000000000100000 D
0%
#25
14
b0 7
b0 ?
b0 5
b0 B
b11 .
b11 \
b10000000000000000000000000010100 -
b10000000000000000000000000010100 ]
12
b1000 6
b1000 A
b1000 Z
03
b0 +
b0 _
b0 a
b0 ,
b0 ^
b0 c
b11111111111111111111111111100000 N
b11111111111100000000011111100000 M
b11111111111111111111111111110100 O
b11111111111111111111111111110101 L
b0 '
b0 *
b0 @
b0 f
b1100011 H
b10101 G
b0 F
b0 E
b1111111 I
b11111110000000000000000000000000 K
b11111110000000000000101011100011 9
b11111110000000000000101011100011 C
1%
#26
b10000000000000000000000000001000 -
b10000000000000000000000000001000 ]
b1100010000100001100011 #
b1100010000100001100011 1
b1100010000100001100011 j
b101 i
b10000000000000000000000000010100 $
b10000000000000000000000000010100 :
b10000000000000000000000000010100 h
b10000000000000000000000000010100 =
b10000000000000000000000000010100 D
b0 >
b0 d
0%
#27
04
b11111111111111111111111111110011 5
b11111111111111111111111111110011 B
b10000 7
b10000 ?
b10000 (
b10000 e
b11 '
b11 *
b11 @
b11 f
b10000000000000000000000000100100 -
b10000000000000000000000000100100 ]
b11 )
b11 `
b11 b
b10 +
b10 _
b10 a
b11 N
b10000100000000010 M
b10000 O
b10000 L
b10000 G
b10 F
b11 E
b0 I
b1100010000000000000000 K
b1100010000100001100011 9
b1100010000100001100011 C
1%
#28
b10000000000000000000000000101000 -
b10000000000000000000000000101000 ]
b1000100000001000110011 #
b1000100000001000110011 1
b1000100000001000110011 j
b110 i
b10000000000000000000000000011000 $
b10000000000000000000000000011000 :
b10000000000000000000000000011000 h
b10000000000000000000000000011000 =
b10000000000000000000000000011000 D
b11111111111111111111111111110011 >
b11111111111111111111111111110011 d
0%
#29
b110 5
b110 B
b11 7
b11 ?
b11 (
b11 e
b0 .
b0 \
02
b0 6
b0 A
b0 Z
b10 )
b10 `
b10 b
b100 +
b100 _
b100 a
b100 ,
b100 ^
b100 c
b10 N
b100000000000000010 M
b100 O
b100 L
b110011 H
b100 G
b100 F
b10 E
b1000100000000000000000 K
b1000100000001000110011 9
b1000100000001000110011 C
1%
#30
b100010000000100010011 #
b100010000000100010011 1
b100010000000100010011 j
b111 i
b10000000000000000000000000011100 $
b10000000000000000000000000011100 :
b10000000000000000000000000011100 h
b10000000000000000000000000011100 =
b10000000000000000000000000011100 D
b110 >
b110 d
0%
#31
b1 7
b1 ?
b0 (
b0 e
b1 /
b1 [
13
b0 )
b0 `
b0 b
b10 +
b10 _
b10 a
b10 ,
b10 ^
b10 c
b100 5
b100 B
b1 N
b10000100000000000 M
b10 O
b10 L
b10011 H
b10 G
b10 F
b1 E
b100010000000000000000 K
b11 '
b11 *
b11 @
b11 f
b100010000000100010011 9
b100010000000100010011 C
1%
#32
b11111110000000000000101011100011 #
b11111110000000000000101011100011 1
b11111110000000000000101011100011 j
b1000 i
b10000000000000000000000000100000 $
b10000000000000000000000000100000 :
b10000000000000000000000000100000 h
b10000000000000000000000000100000 =
b10000000000000000000000000100000 D
b100 >
b100 d
0%
#33
14
b0 7
b0 ?
b0 5
b0 B
b11 .
b11 \
b10000000000000000000000000010100 -
b10000000000000000000000000010100 ]
12
b1000 6
b1000 A
b1000 Z
03
b0 +
b0 _
b0 a
b0 ,
b0 ^
b0 c
b11111111111111111111111111100000 N
b11111111111100000000011111100000 M
b11111111111111111111111111110100 O
b11111111111111111111111111110101 L
b0 '
b0 *
b0 @
b0 f
b1100011 H
b10101 G
b0 F
b0 E
b1111111 I
b11111110000000000000000000000000 K
b11111110000000000000101011100011 9
b11111110000000000000101011100011 C
1%
#34
b10000000000000000000000000001000 -
b10000000000000000000000000001000 ]
b1100010000100001100011 #
b1100010000100001100011 1
b1100010000100001100011 j
b101 i
b10000000000000000000000000010100 $
b10000000000000000000000000010100 :
b10000000000000000000000000010100 h
b10000000000000000000000000010100 =
b10000000000000000000000000010100 D
b0 >
b0 d
0%
#35
04
b11111111111111111111111111110100 5
b11111111111111111111111111110100 B
b10000 7
b10000 ?
b10000 (
b10000 e
b100 '
b100 *
b100 @
b100 f
b10000000000000000000000000100100 -
b10000000000000000000000000100100 ]
b11 )
b11 `
b11 b
b10 +
b10 _
b10 a
b11 N
b10000100000000010 M
b10000 O
b10000 L
b10000 G
b10 F
b11 E
b0 I
b1100010000000000000000 K
b1100010000100001100011 9
b1100010000100001100011 C
1%
#36
b10000000000000000000000000101000 -
b10000000000000000000000000101000 ]
b1000100000001000110011 #
b1000100000001000110011 1
b1000100000001000110011 j
b110 i
b10000000000000000000000000011000 $
b10000000000000000000000000011000 :
b10000000000000000000000000011000 h
b10000000000000000000000000011000 =
b10000000000000000000000000011000 D
b11111111111111111111111111110100 >
b11111111111111111111111111110100 d
0%
#37
b1010 5
b1010 B
b100 7
b100 ?
b100 (
b100 e
b110 '
b110 *
b110 @
b110 f
b0 .
b0 \
02
b0 6
b0 A
b0 Z
b10 )
b10 `
b10 b
b100 +
b100 _
b100 a
b100 ,
b100 ^
b100 c
b10 N
b100000000000000010 M
b100 O
b100 L
b110011 H
b100 G
b100 F
b10 E
b1000100000000000000000 K
b1000100000001000110011 9
b1000100000001000110011 C
1%
