ALU.v


module ALU (
    input   wire            i_clk,
    input   wire    [31:0]  i_input_a,
    input   wire    [31:0]  i_input_b,
    input   wire    [3:0]   i_alu_op,
    output  reg     [31:0]  o_result,
    output  reg             o_zero
);
    initial begin
        o_result = 32'h00000000;
        o_zero = 1'b0;
    end
    
    always @(posedge i_clk) begin
        case(i_alu_op[3:0])
            // ADD
            4'b0000: o_result <= i_input_a + i_input_b ;
            // SLL
            4'b0001: o_result <= i_input_a << i_input_b[4:0];
            // SLT
            4'b0010: o_result <= $signed(i_input_a) < $signed(i_input_b) ? 1 : 0;
            // SLTU
            4'b0011: o_result <= i_input_a < i_input_b ? 1 : 0;
            // XOR
            4'b0100: o_result <= i_input_a ^ i_input_b;
            // SRL
            4'b0101: o_result <= i_input_a >> i_input_b[4:0];
            // OR
            4'b0110: o_result <= i_input_a | i_input_b;
            // AND
            4'b0111: o_result <= i_input_a & i_input_b;
            // SUB
            4'b1000: o_result <= i_input_a - i_input_b ;
            // SRA
            4'b1101: o_result <= $signed(i_input_a) >>> i_input_b[4:0];
            // BNE
            4'b1111: o_result <= i_input_a != i_input_b ? 0 : 1;
            // BLT
            4'b1100: o_result <= $signed(i_input_a) < $signed(i_input_b) ? 0 : 1;
            // BGE
            4'b1011: o_result <= $signed(i_input_a) >= $signed(i_input_b) ? 0 : 1;
            // BLTU
            4'b1010: o_result <= i_input_a < i_input_b ? 0 : 1;
            // BGEU
            4'b1001: o_result <= i_input_a >= i_input_b ? 0 : 1;
            default: o_result <= 32'h00000000;
        endcase
        o_zero <= o_result == 32'h00000000;
    end

endmodule

Decoder.v



module Decoder (
    input   wire    [31:0]  i_opcode,
    input   wire    [31:0]  i_pc,
    output  reg     [4:0]   o_rd,
    output  reg     [4:0]   o_rs1,
    output  reg     [4:0]   o_rs2,
    output  reg             o_en_imm,
    output  reg     [31:0]  o_imm,
    output  reg             o_en_jump,
    output  reg     [31:0]  o_jump_addr,
    output  reg     [3:0]   o_alu_op,
    output  reg     [1:0]   o_jump,
    output  reg             o_illegal_instruction
);
    wire    [6:0]   opcode;
    wire    [4:0]   rd;
    wire    [2:0]   funct3;
    wire    [4:0]   rs1;
    wire    [4:0]   rs2;
    wire    [6:0]   funct7;
    wire    [31:0]  I_immediate;
    wire    [31:0]  U_immediate;
    wire    [31:0]  J_immediate;
    wire    [31:0]  B_immediate;
    wire    [31:0]  S_immediate;
    
    

    initial begin
        o_rd                    = 0;
        o_rs1                   = 0;
        o_rs2                   = 0;
        o_en_imm                = 0;
        o_imm                   = 0;
        o_en_jump               = 0;
        o_jump_addr             = 0;
        o_alu_op                = 0;
        o_jump                  = 0;
        o_illegal_instruction   = 1;
    end

    assign opcode       = i_opcode[6:0];
    assign rd           = i_opcode[11:7];
    assign funct3       = i_opcode[14:12];
    assign rs1          = i_opcode[19:15];
    assign rs2          = i_opcode[24:20];
    assign funct7       = i_opcode[31:25];
    assign I_immediate  = i_opcode[31] ? {{20{1'b1}},i_opcode[31:20]} : {{20{1'b0}},i_opcode[31:20]};
    assign U_immediate  = {i_opcode[31:12],{12{1'b0}}};
    assign J_immediate  = i_opcode[31] ? {{12{1'b1}},i_opcode[19:12],i_opcode[20],i_opcode[30:25],i_opcode[24:21],1'b0}
                                       : {{12{1'b0}},i_opcode[19:12],i_opcode[20],i_opcode[30:25],i_opcode[24:21],1'b0};
    assign B_immediate  = i_opcode[31] ? {{20{1'b1}},i_opcode[7],i_opcode[30:25],i_opcode[11:8],1'b0}
                                       : {{20{1'b0}},i_opcode[7],i_opcode[30:25],i_opcode[11:8],1'b0};
    assign S_immediate  = i_opcode[31] ? {{20{1'b1}},i_opcode[31:25],i_opcode[11:8],i_opcode[7]}
                                       : {{20{1'b0}},i_opcode[31:25],i_opcode[11:8],i_opcode[7]};

    parameter opcode_OP         = 7'b0110011;
    parameter opcode_OP_IMM     = 7'b0010011;
    parameter opcode_SYSTEM     = 7'b1110011;
    parameter opcode_AUIPC      = 7'b0010111;
    parameter opcode_LUI        = 7'b0110111;
    parameter opcode_JAL        = 7'b1101111;
    parameter opcode_JALR       = 7'b1100111;
    parameter opcode_BRANCH     = 7'b1100011;
    parameter opcode_LOAD       = 7'b0000011;
    parameter opcode_STORE      = 7'b0100011;

    always @(*) begin
        case(opcode)
            opcode_OP: begin
                o_rd                    <= rd;
                o_rs1                   <= rs1;
                o_rs2                   <= rs2;
                o_en_imm                <= 0;
                o_alu_op                <= {funct7[5],funct3};
                o_en_jump               <= 0;
                o_jump                  <= 0;
                o_illegal_instruction   <= 0;
            end
            opcode_OP_IMM: begin
                o_rd                    <= rd;
                o_rs1                   <= rs1;
                o_rs2                   <= 0;
                o_en_imm                <= 1;
                o_imm                   <= (funct3 == 3'b001 || funct3 == 3'b101) ? 
                                           {{27{1'b0}},rs2} :                                     // for shift 
                                           I_immediate;
                o_alu_op                <= (funct3 == 3'b001 || funct3 == 3'b101) ? 
                                           {funct7[5],funct3} :                                   // for shift
                                           funct3;
                o_en_jump               <= 0;
                o_jump                  <= 0;
                o_illegal_instruction   <= 0;
            end
            opcode_AUIPC: begin
                o_rd                    <= rd;
                o_rs1                   <= 0;
                o_rs2                   <= 0;
                o_en_imm                <= 1;
                o_imm                   <= U_immediate;
                o_en_jump               <= 1;
                o_jump_addr             <= i_pc;
                o_alu_op                <= 4'b0000; // add
                o_jump                  <= 0;
                o_illegal_instruction   <= 0;
            end
            opcode_LUI: begin
                o_rd                    <= rd;
                o_rs1                   <= 0;
                o_rs2                   <= 0;
                o_en_imm                <= 1;
                o_imm                   <= U_immediate;
                o_en_jump               <= 0;
                o_jump_addr             <= 0;
                o_alu_op                <= 4'b0000; // add
                o_jump                  <= 0;
                o_illegal_instruction   <= 0;
            end
            opcode_JAL: begin
                o_rd                    <= rd;
                o_rs1                   <= 0;
                o_rs2                   <= 0;
                o_en_imm                <= 1;
                o_imm                   <= i_pc + 4;
                o_en_jump               <= 1;
                o_jump_addr             <= i_pc + J_immediate;
                o_alu_op                <= 4'b0000; // add
                o_jump                  <= 1;
                o_illegal_instruction   <= 0;
            end
            opcode_JALR: begin
                o_rd                    <= rd;
                o_rs1                   <= rs1;
                o_rs2                   <= 0;
                o_en_imm                <= 1;
                o_imm                   <= I_immediate;
                o_en_jump               <= 1;
                o_jump_addr             <= i_pc + 4;
                o_alu_op                <= 4'b0000; // add
                o_jump                  <= 2;
                o_illegal_instruction   <= 0;
            end
            opcode_BRANCH: begin
                o_rd                    <= 0;
                o_rs1                   <= rs1;
                o_rs2                   <= rs2;
                o_en_imm                <= 1;
                o_alu_op                <= {1'b1,-funct3};
                o_en_jump               <= 1;
                o_jump                  <= 3;
                o_illegal_instruction   <= 0;
            end
            default: begin
                o_rd                    <= 0;
                o_rs1                   <= 0;
                o_rs2                   <= 0;
                o_en_imm                <= 0;
                o_illegal_instruction   <= 1;
            end
        endcase
    end

endmodule

RegFile.v
module RegFile (
    input   wire            i_clk,
    input   wire    [31:0]  i_wdata,
    input   wire    [4:0]   i_waddr,
    output  wire    [31:0]  o_r1data,
    input   wire    [4:0]   i_r1addr,
    output  wire    [31:0]  o_r2data,
    input   wire    [4:0]   i_r2addr
);

    reg [31:0] register [31:0];

    reg [31:0] r1data;
    reg [31:0] r2data;

    integer i;

    initial begin
        for (i = 0; i < 32; i = i + 1) begin
            register[i] = 32'h00000000;
        end

        r1data = 32'h00000000;
        r2data = 32'h00000000;
    end

    always @(negedge i_clk) begin
        register[i_waddr] <= i_wdata;
        case (i_r1addr)
            5'h00: r1data <= 32'h00000000;
            default: r1data <= register[i_r1addr];
        endcase

        case (i_r2addr)
            5'h00: r2data <= 32'h00000000;
            default: r2data <= register[i_r2addr];
        endcase
    end

    assign o_r1data = r1data;
    assign o_r2data = r2data;


endmodule

CPU.v
`include "ALU.v"
`include "Decoder.v"
`include "RegFile.v"


module cpu (
    input   wire            i_clk,
    input   wire            i_nreset,
    input   wire    [31:0]  i_membus,
    output  reg             o_memwrite,
    output  reg             o_memread,
    output  reg     [31:0]  o_memaddr
);
    reg     [31:0]  pc = 32'h80000000;    

    reg     [31:0]  insn = 32'h00000000;
    wire    [4:0]   rd;
    wire    [4:0]   rs1;
    wire    [31:0]  rs1data;
    wire    [4:0]   rs2;
    wire    [31:0]  rs2data;
    wire            en_imm;
    wire    [31:0]  imm;
    wire            en_jump;
    wire    [31:0]  jump_addr;
    wire    [3:0]   alu_op;
    wire    [1:0]   jump;
    wire            illegal_instruction;
    wire    [31:0]  alu_result;
    reg     [31:0]  reg_wdata   = 32'h00000000;
    wire    [31:0]  alu_input_b;
    wire            cond;

    initial begin
        o_memwrite = 1'b0;
        o_memread  = 1'b1;
        o_memaddr  = 32'h00000000;
    end

    assign alu_input_b = en_imm ? imm : rs2data;

    RegFile reg_file (
        .i_clk      (i_clk),
        .i_wdata    (reg_wdata),
        .i_waddr    (rd),
        .o_r1data   (rs1data),
        .i_r1addr   (rs1),
        .o_r2data   (rs2data),
        .i_r2addr   (rs2)
    );

    Decoder decoder (
        .i_opcode               (insn),
        .i_pc                   (pc),
        .o_rd                   (rd),
        .o_rs1                  (rs1),
        .o_rs2                  (rs2),
        .o_en_imm               (en_imm),
        .o_imm                  (imm),
        .o_en_jump              (en_jump),
        .o_jump_addr            (jump_addr),
        .o_alu_op               (alu_op),
        .o_jump                 (jump),
        .o_illegal_instruction  (illegal_instruction)
    );

    ALU alu (
        .i_clk      (i_clk),
        .i_alu_op   (alu_op),
        .i_input_a  (rs1data),
        .i_input_b  (alu_input_b),
        .o_result   (alu_result),
        .o_zero     (cond)
    );

    always @(posedge i_clk) begin
    end

    always @(posedge i_clk or negedge i_nreset) begin
        if (!i_nreset) begin
            pc <= 32'h80000000;
        end
        else begin
            case (jump)
                2'b00: begin
                    reg_wdata <= alu_result;        // no jump
                    pc        <= pc + 4;
                end
                2'b01: begin
                    reg_wdata <= alu_result;        // jal
                    pc        <= jump_addr;
                end
                2'b10: begin
                    reg_wdata <= jump_addr;         // jalr
                    pc        <= alu_result;
                end
                2'b11: begin
                    reg_wdata <= alu_result;        // branch
                    if (cond) begin
                        pc <= jump_addr;
                    end else begin
                        pc <= pc + 4;
                    end
                end
            endcase
            o_memaddr = pc;
            insn      = i_membus;
        end
    end


endmodule

CPU_tb.v
module Memory (
    input   wire            i_clk,
    input   wire            i_memread,
    input   wire    [31:0]  i_memaddr,
    output  reg     [31:0]  o_membus
);

    reg [31:0] memory [0:255];
    wire [31:0] addr;

    initial begin
        $readmemh("test.hex", memory);
    end

    always @(*) begin
        o_membus = memory[addr];
    end


    assign addr = (32'h80000000 <= i_memaddr && i_memaddr <= 32'h800003fc) ? (i_memaddr - 32'h80000000) >> 2 : 32'h00000000;
                                 

endmodule



module CPU_tb;
    reg             clk = 1'b0;
    wire            memwrite = 1'b0;
    wire            memread = 1'b1;
    wire    [31:0]  memaddr;
    wire    [31:0]  membus;
    reg             nreset = 1'b0;

    Memory mem (
        .i_clk      (clk),
        .i_memread  (memread),
        .i_memaddr  (memaddr),
        .o_membus   (membus)
    );

    cpu DUT (
        .i_clk      (clk),
        .i_nreset   (nreset),
        .o_memaddr  (memaddr),
        .o_memwrite (memwrite),
        .o_memread  (memread),
        .i_membus   (membus)
    );


    initial begin
        $dumpfile("CPU.vcd");
        $dumpvars(0);
    end

    always #1 begin
        clk = ~clk;
    end


    initial begin
        #2
        nreset = 1'b1;
        #16
        $finish;
    end


endmodule

CPU.vcd
$date
	Wed Oct  2 22:42:44 2024
$end
$version
	Icarus Verilog
$end
$timescale
	1s
$end
$scope module CPU_tb $end
$var wire 1 ! memread $end
$var wire 1 " memwrite $end
$var wire 32 # membus [31:0] $end
$var wire 32 $ memaddr [31:0] $end
$var reg 1 % clk $end
$var reg 1 & nreset $end
$scope module DUT $end
$var wire 1 % i_clk $end
$var wire 1 & i_nreset $end
$var wire 32 ' rs2data [31:0] $end
$var wire 5 ( rs2 [4:0] $end
$var wire 32 ) rs1data [31:0] $end
$var wire 5 * rs1 [4:0] $end
$var wire 5 + rd [4:0] $end
$var wire 32 , jump_addr [31:0] $end
$var wire 2 - jump [1:0] $end
$var wire 32 . imm [31:0] $end
$var wire 1 / illegal_instruction $end
$var wire 32 0 i_membus [31:0] $end
$var wire 1 1 en_jump $end
$var wire 1 2 en_imm $end
$var wire 1 3 cond $end
$var wire 32 4 alu_result [31:0] $end
$var wire 4 5 alu_op [3:0] $end
$var wire 32 6 alu_input_b [31:0] $end
$var reg 32 7 insn [31:0] $end
$var reg 32 8 o_memaddr [31:0] $end
$var reg 1 9 o_memread $end
$var reg 1 : o_memwrite $end
$var reg 32 ; pc [31:0] $end
$var reg 32 < reg_wdata [31:0] $end
$scope module alu $end
$var wire 1 % i_clk $end
$var wire 32 = i_input_b [31:0] $end
$var wire 32 > i_input_a [31:0] $end
$var wire 4 ? i_alu_op [3:0] $end
$var reg 32 @ o_result [31:0] $end
$var reg 1 3 o_zero $end
$upscope $end
$scope module decoder $end
$var wire 32 A i_opcode [31:0] $end
$var wire 32 B i_pc [31:0] $end
$var wire 5 C rs2 [4:0] $end
$var wire 5 D rs1 [4:0] $end
$var wire 5 E rd [4:0] $end
$var wire 7 F opcode [6:0] $end
$var wire 7 G funct7 [6:0] $end
$var wire 3 H funct3 [2:0] $end
$var wire 32 I U_immediate [31:0] $end
$var wire 32 J S_immediate [31:0] $end
$var wire 32 K J_immediate [31:0] $end
$var wire 32 L I_immediate [31:0] $end
$var wire 32 M B_immediate [31:0] $end
$var parameter 7 N opcode_AUIPC $end
$var parameter 7 O opcode_BRANCH $end
$var parameter 7 P opcode_JAL $end
$var parameter 7 Q opcode_JALR $end
$var parameter 7 R opcode_LOAD $end
$var parameter 7 S opcode_LUI $end
$var parameter 7 T opcode_OP $end
$var parameter 7 U opcode_OP_IMM $end
$var parameter 7 V opcode_STORE $end
$var parameter 7 W opcode_SYSTEM $end
$var reg 4 X o_alu_op [3:0] $end
$var reg 1 2 o_en_imm $end
$var reg 1 1 o_en_jump $end
$var reg 1 / o_illegal_instruction $end
$var reg 32 Y o_imm [31:0] $end
$var reg 2 Z o_jump [1:0] $end
$var reg 32 [ o_jump_addr [31:0] $end
$var reg 5 \ o_rd [4:0] $end
$var reg 5 ] o_rs1 [4:0] $end
$var reg 5 ^ o_rs2 [4:0] $end
$upscope $end
$scope module reg_file $end
$var wire 1 % i_clk $end
$var wire 5 _ i_r1addr [4:0] $end
$var wire 5 ` i_r2addr [4:0] $end
$var wire 5 a i_waddr [4:0] $end
$var wire 32 b i_wdata [31:0] $end
$var wire 32 c o_r1data [31:0] $end
$var wire 32 d o_r2data [31:0] $end
$var reg 32 e r1data [31:0] $end
$var reg 32 f r2data [31:0] $end
$var integer 32 g i [31:0] $end
$upscope $end
$upscope $end
$scope module mem $end
$var wire 1 % i_clk $end
$var wire 32 h i_memaddr [31:0] $end
$var wire 1 ! i_memread $end
$var wire 32 i addr [31:0] $end
$var reg 32 j o_membus [31:0] $end
$upscope $end
$upscope $end
$enddefinitions $end
$comment Show the parameter values. $end
$dumpall
b1110011 W
b100011 V
b10011 U
b110011 T
b110111 S
b11 R
b1100111 Q
b1101111 P
b1100011 O
b10111 N
$end
#0
$dumpvars
b10010001101000101000010110111 j
b0 i
b0 h
b100000 g
b0 f
b0 e
b0 d
b0 c
b0 b
b0 a
b0 `
b0 _
b0 ^
b0 ]
b0 \
b0 [
b0 Z
b0 Y
b0 X
b0 M
b0 L
b0 K
b0 J
b0 I
b0 H
b0 G
b0 F
b0 E
b0 D
b0 C
b10000000000000000000000000000000 B
b0 A
b0 @
b0 ?
b0 >
b0 =
b0 <
b10000000000000000000000000000000 ;
0:
19
b0 8
b0 7
b0 6
b0 5
b0 4
03
02
01
b10010001101000101000010110111 0
1/
b0 .
b0 -
b0 ,
b0 +
b0 *
b0 )
b0 (
b0 '
0&
0%
b0 $
b10010001101000101000010110111 #
0"
1!
$end
#1
13
1%
#2
0%
1&
#3
b10010001101000101000000000000 6
b10010001101000101000000000000 =
0/
b10010001101000101000000000000 .
b10010001101000101000000000000 Y
12
b1 +
b1 \
b1 a
b10000000000000000000000000000100 ;
b10000000000000000000000000000100 B
b100100011 L
b1000101100100100010 K
b100100100000 M
b100100001 J
b110111 F
b1 E
b101 H
b1000 D
b11 C
b1001 G
b10010001101000101000000000000 I
b10010001101000101000010110111 7
b10010001101000101000010110111 A
b10000000000000000000000000000000 $
b10000000000000000000000000000000 8
b10000000000000000000000000000000 h
1%
#4
0%
#5
b10010001101000101000000000000 4
b10010001101000101000000000000 @
b10000000000000000000000000001000 ;
b10000000000000000000000000001000 B
b1100111100000001000000010010011 #
b1100111100000001000000010010011 0
b1100111100000001000000010010011 j
b1 i
b10000000000000000000000000000100 $
b10000000000000000000000000000100 8
b10000000000000000000000000000100 h
1%
#6
0%
#7
b11001111000 6
b11001111000 =
b11001111000 .
b11001111000 Y
b1 *
b1 ]
b1 _
03
b10000000000000000000000000001100 ;
b10000000000000000000000000001100 B
b10010001101000101000000000000 <
b10010001101000101000000000000 b
b1000000000110011 #
b1000000000110011 0
b1000000000110011 j
b11001111000 L
b1000011001111000 K
b111001100000 M
b11001100001 J
b10 i
b10011 F
b0 H
b1 D
b11000 C
b110011 G
b1100111100000001000000000000000 I
b1100111100000001000000010010011 7
b1100111100000001000000010010011 A
b10000000000000000000000000001000 $
b10000000000000000000000000001000 8
b10000000000000000000000000001000 h
1%
#8
0%
#9
b0 6
b0 =
02
b0 +
b0 \
b0 a
b11001111000 4
b11001111000 @
b10000000000000000000000000010000 ;
b10000000000000000000000000010000 B
b0 L
b1000000000000000 K
b0 M
b0 J
b11 i
b110011 F
b0 E
b0 C
b0 G
b1000000000000000 I
b1000000000110011 7
b1000000000110011 A
b10000000000000000000000000001100 $
b10000000000000000000000000001100 8
b10000000000000000000000000001100 h
1%
#10
b10010001101000101000000000000 )
b10010001101000101000000000000 >
b10010001101000101000000000000 c
b10010001101000101000000000000 e
0%
#11
b10010001101000101000000000000 4
b10010001101000101000000000000 @
b10000000000000000000000000010100 ;
b10000000000000000000000000010100 B
b11001111000 <
b11001111000 b
b100 i
b10000000000000000000000000010000 $
b10000000000000000000000000010000 8
b10000000000000000000000000010000 h
1%
#12
0%
#13
b10000000000000000000000000011000 ;
b10000000000000000000000000011000 B
b10010001101000101000000000000 <
b10010001101000101000000000000 b
b101 i
b10000000000000000000000000010100 $
b10000000000000000000000000010100 8
b10000000000000000000000000010100 h
1%
#14
0%
#15
b10000000000000000000000000011100 ;
b10000000000000000000000000011100 B
b110 i
b10000000000000000000000000011000 $
b10000000000000000000000000011000 8
b10000000000000000000000000011000 h
1%
#16
0%
#17
b10000000000000000000000000100000 ;
b10000000000000000000000000100000 B
b111 i
b10000000000000000000000000011100 $
b10000000000000000000000000011100 8
b10000000000000000000000000011100 h
1%
