Decoder.v



module Decoder (
    input   wire    [31:0]  i_opcode,
    input   wire    [31:0]  i_pc,
    output  reg     [4:0]   o_rd,
    output  reg     [4:0]   o_rs1,
    output  reg     [4:0]   o_rs2,
    output  reg             o_en_imm,
    output  reg     [31:0]  o_imm,
    output  reg             o_en_jump,
    output  reg     [31:0]  o_jump_addr,
    output  reg     [3:0]   o_alu_op,
    output  reg     [1:0]   o_jump,
    output  reg             o_illegal_instruction
);
    wire    [6:0]   opcode;
    wire    [4:0]   rd;
    wire    [2:0]   funct3;
    wire    [4:0]   rs1;
    wire    [4:0]   rs2;
    wire    [6:0]   funct7;
    wire    [31:0]  I_immediate;
    wire    [31:0]  U_immediate;
    wire    [31:0]  J_immediate;
    wire    [31:0]  B_immediate;
    wire    [31:0]  S_immediate;
    
    

    initial begin
        o_rd                    = 0;
        o_rs1                   = 0;
        o_rs2                   = 0;
        o_en_imm                = 0;
        o_imm                   = 0;
        o_en_jump               = 0;
        o_jump_addr             = 0;
        o_alu_op                = 0;
        o_jump                  = 0;
        o_illegal_instruction   = 1;
    end

    assign opcode       = i_opcode[6:0];
    assign rd           = i_opcode[11:7];
    assign funct3       = i_opcode[14:12];
    assign rs1          = i_opcode[19:15];
    assign rs2          = i_opcode[24:20];
    assign funct7       = i_opcode[31:25];
    assign I_immediate  = i_opcode[31] ? {{20{1'b1}},i_opcode[31:20]} : {{20{1'b0}},i_opcode[31:20]};
    assign U_immediate  = {i_opcode[31:12],{12{1'b0}}};
    assign J_immediate  = i_opcode[31] ? {{12{1'b1}},i_opcode[19:12],i_opcode[20],i_opcode[30:25],i_opcode[24:21],1'b0}
                                       : {{12{1'b0}},i_opcode[19:12],i_opcode[20],i_opcode[30:25],i_opcode[24:21],1'b0};
    assign B_immediate  = i_opcode[31] ? {{20{1'b1}},i_opcode[7],i_opcode[30:25],i_opcode[11:8],1'b0}
                                       : {{20{1'b0}},i_opcode[7],i_opcode[30:25],i_opcode[11:8],1'b0};
    assign S_immediate  = i_opcode[31] ? {{20{1'b1}},i_opcode[31:25],i_opcode[11:8],i_opcode[7]}
                                       : {{20{1'b0}},i_opcode[31:25],i_opcode[11:8],i_opcode[7]};

    parameter opcode_OP         = 7'b0110011;
    parameter opcode_OP_IMM     = 7'b0010011;
    parameter opcode_SYSTEM     = 7'b1110011;
    parameter opcode_AUIPC      = 7'b0010111;
    parameter opcode_LUI        = 7'b0110111;
    parameter opcode_JAL        = 7'b1101111;
    parameter opcode_JALR       = 7'b1100111;
    parameter opcode_BRANCH     = 7'b1100011;
    parameter opcode_LOAD       = 7'b0000011;
    parameter opcode_STORE      = 7'b0100011;

    always @(*) begin
        case(opcode)
            opcode_OP: begin
                o_rd                    <= rd;
                o_rs1                   <= rs1;
                o_rs2                   <= rs2;
                o_en_imm                <= 0;
                o_alu_op                <= {funct7[5],funct3};
                o_en_jump               <= 0;
                o_jump                  <= 0;
                o_illegal_instruction   <= 0;
            end
            opcode_OP_IMM: begin
                o_rd                    <= rd;
                o_rs1                   <= rs1;
                o_rs2                   <= 0;
                o_en_imm                <= 1;
                o_imm                   <= (funct3 == 3'b001 || funct3 == 3'b101) ? 
                                           {{27{1'b0}},rs2} :                                     // for shift 
                                           I_immediate;
                o_alu_op                <= (funct3 == 3'b001 || funct3 == 3'b101) ? 
                                           {funct7[5],funct3} :                                   // for shift
                                           funct3;
                o_en_jump               <= 0;
                o_jump                  <= 0;
                o_illegal_instruction   <= 0;
            end
            opcode_AUIPC: begin
                o_rd                    <= rd;
                o_rs1                   <= 0;
                o_rs2                   <= 0;
                o_en_imm                <= 1;
                o_imm                   <= U_immediate;
                o_en_jump               <= 1;
                o_jump_addr             <= i_pc;
                o_alu_op                <= 4'b0000; // add
                o_jump                  <= 0;
                o_illegal_instruction   <= 0;
            end
            opcode_LUI: begin
                o_rd                    <= rd;
                o_rs1                   <= 0;
                o_rs2                   <= 0;
                o_en_imm                <= 1;
                o_imm                   <= U_immediate;
                o_en_jump               <= 0;
                o_jump_addr             <= 0;
                o_alu_op                <= 4'b0000; // add
                o_jump                  <= 0;
                o_illegal_instruction   <= 0;
            end
            opcode_JAL: begin
                o_rd                    <= rd;
                o_rs1                   <= 0;
                o_rs2                   <= 0;
                o_en_imm                <= 1;
                o_imm                   <= i_pc + 4;
                o_en_jump               <= 1;
                o_jump_addr             <= i_pc + J_immediate;
                o_alu_op                <= 4'b0000; // add
                o_jump                  <= 1;
                o_illegal_instruction   <= 0;
            end
            opcode_JALR: begin
                o_rd                    <= rd;
                o_rs1                   <= rs1;
                o_rs2                   <= 0;
                o_en_imm                <= 1;
                o_imm                   <= I_immediate;
                o_en_jump               <= 1;
                o_jump_addr             <= i_pc + 4;
                o_alu_op                <= 4'b0000; // add
                o_jump                  <= 2;
                o_illegal_instruction   <= 0;
            end
            opcode_BRANCH: begin
                o_rd                    <= 0;
                o_rs1                   <= rs1;
                o_rs2                   <= rs2;
                o_en_imm                <= 1;
                o_alu_op                <= {1'b1,-funct3};
                o_en_jump               <= 1;
                o_jump                  <= 3;
                o_illegal_instruction   <= 0;
            end
            default: begin
                o_rd                    <= 0;
                o_rs1                   <= 0;
                o_rs2                   <= 0;
                o_en_imm                <= 0;
                o_illegal_instruction   <= 1;
            end
        endcase
    end

endmodule

Decoder_tb.v
module decoder_tb;
    reg             clk        = 1'b0;
    reg     [31:0]  opcode     = 32'h00000000;
    reg     [31:0]  pc         = 32'h80000000;
    wire    [4:0]   rd;
    wire    [4:0]   rs1;
    wire    [4:0]   rs2;
    wire            en_imm;
    wire    [31:0]  imm;
    wire            en_jump;
    wire    [31:0]  jump_addr;
    wire    [3:0]   alu_op;
    wire    [1:0]   jump;
    wire            illegal_instruction;


    initial begin
        $dumpfile("Decoder.vcd");
        $dumpvars(0, DUT);
    end

    always #1 begin
        clk <= ~clk;
    end


    Decoder DUT (
        .i_opcode               (opcode),
        .i_pc                   (pc),
        .o_rd                   (rd),
        .o_rs1                  (rs1),
        .o_rs2                  (rs2),
        .o_en_imm               (en_imm),
        .o_imm                  (imm),
        .o_en_jump              (en_jump),
        .o_jump_addr            (jump_addr),
        .o_alu_op               (alu_op),
        .o_jump                 (jump),
        .o_illegal_instruction  (illegal_instruction)
    );

    initial begin
        // addi x0, x0, 0 (nop)
        opcode = 32'h00000013; 
        #2
        // slli x1, x15, 0xc
        opcode = 32'h00c79093;
        #2
        // slti x2, x15, -768
        opcode = 32'hd007a113;
        #2
        // sltiu x3, x15, 0x800
        opcode = 32'h8007b193;
        #2
        // xori x4, x15, 0x800
        opcode = 32'h8007c213;
        #2
        // srli x5, x15, 0xc
        opcode = 32'h00c7d293;
        #2
        // ori x6, x15, 0x800
        opcode = 32'h8007e313;
        #2
        // andi x7, x15, 0x800
        opcode = 32'h8007f393;
        #2
        // srai x13, x15, 0xc
        opcode = 32'h40c7d693;
        #2
        // add x8, x31, x16
        opcode = 32'h010f8433;
        #2
        // sll x9, x31, x17
        opcode = 32'h011f94b3;
        #2
        // slt x10, x31, x18
        opcode = 32'h012fa533;
        #2
        // sltu x11, x31, x19
        opcode = 32'h013fb5b3;
        #2
        // xor x12, x31, x20
        opcode = 32'h014fc633;
        #2
        // srl x13, x31, x21
        opcode = 32'h015fd6b3;
        #2
        // or x14, x31, x22
        opcode = 32'h016fe733;
        #2
        // and x15, x31, x23
        opcode = 32'h017ff7b3;
        #2
        // sub x16, x31, x24
        opcode = 32'h418f8833;
        #2
        // auipc x27, 0
        opcode = 32'h00000d97;
        #2
        // addi x1, x1, 0x678
        opcode = 32'h67808093;
        #2
        #1
        $finish;
    end




endmodule

Decoder.vcd
$date
	Wed Oct  2 22:46:04 2024
$end
$version
	Icarus Verilog
$end
$timescale
	1s
$end
$scope module decoder_tb $end
$scope module DUT $end
$var wire 32 ! i_opcode [31:0] $end
$var wire 32 " i_pc [31:0] $end
$var wire 5 # rs2 [4:0] $end
$var wire 5 $ rs1 [4:0] $end
$var wire 5 % rd [4:0] $end
$var wire 7 & opcode [6:0] $end
$var wire 7 ' funct7 [6:0] $end
$var wire 3 ( funct3 [2:0] $end
$var wire 32 ) U_immediate [31:0] $end
$var wire 32 * S_immediate [31:0] $end
$var wire 32 + J_immediate [31:0] $end
$var wire 32 , I_immediate [31:0] $end
$var wire 32 - B_immediate [31:0] $end
$var parameter 7 . opcode_AUIPC $end
$var parameter 7 / opcode_BRANCH $end
$var parameter 7 0 opcode_JAL $end
$var parameter 7 1 opcode_JALR $end
$var parameter 7 2 opcode_LOAD $end
$var parameter 7 3 opcode_LUI $end
$var parameter 7 4 opcode_OP $end
$var parameter 7 5 opcode_OP_IMM $end
$var parameter 7 6 opcode_STORE $end
$var parameter 7 7 opcode_SYSTEM $end
$var reg 4 8 o_alu_op [3:0] $end
$var reg 1 9 o_en_imm $end
$var reg 1 : o_en_jump $end
$var reg 1 ; o_illegal_instruction $end
$var reg 32 < o_imm [31:0] $end
$var reg 2 = o_jump [1:0] $end
$var reg 32 > o_jump_addr [31:0] $end
$var reg 5 ? o_rd [4:0] $end
$var reg 5 @ o_rs1 [4:0] $end
$var reg 5 A o_rs2 [4:0] $end
$upscope $end
$upscope $end
$enddefinitions $end
$comment Show the parameter values. $end
$dumpall
b1110011 7
b100011 6
b10011 5
b110011 4
b110111 3
b11 2
b1100111 1
b1101111 0
b1100011 /
b10111 .
$end
#0
$dumpvars
b0 A
b0 @
b0 ?
b0 >
b0 =
b0 <
0;
0:
19
b0 8
b0 -
b0 ,
b0 +
b0 *
b0 )
b0 (
b0 '
b10011 &
b0 %
b0 $
b0 #
b10000000000000000000000000000000 "
b10011 !
$end
#2
b1 8
b1100 <
b1111 @
b1 ?
b1100 ,
b1111001000000001100 +
b100000000000 -
b1 *
b1 %
b1 (
b1111 $
b1100 #
b110001111001000000000000 )
b110001111001000010010011 !
#4
b11111111111111111111110100000000 <
b10 8
b10 ?
b11111111111111111111110100000000 ,
b11111111111101111010010100000000 +
b11111111111111111111010100000010 -
b11111111111111111111110100000010 *
b10 %
b10 (
b0 #
b1101000 '
b11010000000001111010000000000000 )
b11010000000001111010000100010011 !
#6
b11111111111111111111100000000000 <
b11 8
b11 ?
b11111111111111111111100000000000 ,
b11111111111101111011000000000000 +
b11111111111111111111100000000010 -
b11111111111111111111100000000011 *
b11 %
b11 (
b1000000 '
b10000000000001111011000000000000 )
b10000000000001111011000110010011 !
#8
b100 8
b100 ?
b11111111111101111100000000000000 +
b11111111111111111111000000000100 -
b11111111111111111111100000000100 *
b100 %
b100 (
b10000000000001111100000000000000 )
b10000000000001111100001000010011 !
#10
b101 8
b1100 <
b101 ?
b1100 ,
b1111101000000001100 +
b100000000100 -
b101 *
b101 %
b101 (
b1100 #
b0 '
b110001111101000000000000 )
b110001111101001010010011 !
#12
b11111111111111111111100000000000 <
b110 8
b110 ?
b11111111111111111111100000000000 ,
b11111111111101111110000000000000 +
b11111111111111111111000000000110 -
b11111111111111111111100000000110 *
b110 %
b110 (
b0 #
b1000000 '
b10000000000001111110000000000000 )
b10000000000001111110001100010011 !
#14
b111 8
b111 ?
b11111111111101111111000000000000 +
b11111111111111111111100000000110 -
b11111111111111111111100000000111 *
b111 %
b111 (
b10000000000001111111000000000000 )
b10000000000001111111001110010011 !
#16
b1101 8
b1100 <
b1101 ?
b10000001100 ,
b1111101010000001100 +
b110000001100 -
b10000001101 *
b1101 %
b101 (
b1100 #
b100000 '
b1000000110001111101000000000000 )
b1000000110001111101011010010011 !
#18
b0 8
09
b10000 A
b11111 @
b1000 ?
b10000 ,
b11111000000000010000 +
b1000 -
b1000 *
b110011 &
b1000 %
b0 (
b11111 $
b10000 #
b0 '
b1000011111000000000000000 )
b1000011111000010000110011 !
#20
b1 8
b10001 A
b1001 ?
b10001 ,
b11111001100000010000 +
b100000001000 -
b1001 *
b1001 %
b1 (
b10001 #
b1000111111001000000000000 )
b1000111111001010010110011 !
#22
b10 8
b10010 A
b1010 ?
b10010 ,
b11111010000000010010 +
b1010 -
b1010 *
b1010 %
b10 (
b10010 #
b1001011111010000000000000 )
b1001011111010010100110011 !
#24
b11 8
b10011 A
b1011 ?
b10011 ,
b11111011100000010010 +
b100000001010 -
b1011 *
b1011 %
b11 (
b10011 #
b1001111111011000000000000 )
b1001111111011010110110011 !
#26
b100 8
b10100 A
b1100 ?
b10100 ,
b11111100000000010100 +
b1100 -
b1100 *
b1100 %
b100 (
b10100 #
b1010011111100000000000000 )
b1010011111100011000110011 !
#28
b101 8
b10101 A
b1101 ?
b10101 ,
b11111101100000010100 +
b100000001100 -
b1101 *
b1101 %
b101 (
b10101 #
b1010111111101000000000000 )
b1010111111101011010110011 !
#30
b110 8
b10110 A
b1110 ?
b10110 ,
b11111110000000010110 +
b1110 -
b1110 *
b1110 %
b110 (
b10110 #
b1011011111110000000000000 )
b1011011111110011100110011 !
#32
b111 8
b10111 A
b1111 ?
b10111 ,
b11111111100000010110 +
b100000001110 -
b1111 *
b1111 %
b111 (
b10111 #
b1011111111111000000000000 )
b1011111111111011110110011 !
#34
b1000 8
b11000 A
b10000 ?
b10000011000 ,
b11111000010000011000 +
b10000010000 -
b10000010000 *
b10000 %
b0 (
b11000 #
b100000 '
b1000001100011111000000000000000 )
b1000001100011111000100000110011 !
#36
b0 8
b10000000000000000000000000000000 >
1:
b0 <
19
b0 A
b0 @
b11011 ?
b0 ,
b0 +
b100000011010 -
b11011 *
b10111 &
b11011 %
b0 $
b0 #
b0 '
b0 )
b110110010111 !
#38
b11001111000 <
0:
b1 @
b1 ?
b11001111000 ,
b1000011001111000 +
b111001100000 -
b11001100001 *
b10011 &
b1 %
b1 $
b11000 #
b110011 '
b1100111100000001000000000000000 )
b1100111100000001000000010010011 !
