RegFile.v
module RegFile (
    input   wire            i_clk,
    input   wire    [31:0]  i_wdata,
    input   wire    [4:0]   i_waddr,
    input   wire            i_wen,
    output  wire    [31:0]  o_r1data,
    input   wire    [4:0]   i_r1addr,
    output  wire    [31:0]  o_r2data,
    input   wire    [4:0]   i_r2addr
);

    reg [31:0] register [31:0];

    reg [31:0] r1data;
    reg [31:0] r2data;

    always @(posedge i_clk) begin
        if (i_wen) begin
            register[i_waddr] = i_wdata;
            r1data <= 32'h00000000;
            r2data <= 32'h00000000;
        end
        else begin
            case (i_r1addr)
                5'h00: r1data <= 32'h00000000;
                default: r1data <= register[i_r1addr];
            endcase

            case (i_r2addr)
                5'h00: r2data <= 32'h00000000;
                default: r2data <= register[i_r2addr];
            endcase
        end
    end

    assign o_r1data = r1data;
    assign o_r2data = r2data;


endmodule

RegFile_tb.v
module RegFile_tb;
    reg             clk         = 1'b0;
    reg     [31:0]  wdata       = 32'h00000000;
    reg     [4:0]   waddr       = 32'h00000000;
    reg             wen         = 1'b0;
    wire    [31:0]  r1data;
    reg     [4:0]   r1addr      = 32'h00000000;
    wire    [31:0]  r2data;
    reg     [4:0]   r2addr      = 32'h00000000;


    initial begin
        $dumpfile("RegFile.vcd");
        $dumpvars(0, DUT);
    end

    always #1 begin
        clk <= ~clk;
    end


    RegFile DUT (
        .i_clk      (clk),
        .i_wdata    (wdata),
        .i_waddr    (waddr),
        .i_wen      (wen),
        .o_r1data   (r1data),
        .i_r1addr   (r1addr),
        .o_r2data   (r2data),
        .i_r2addr   (r2addr)       
    );

    initial begin
        #2
        wen = 1'b1;
        waddr = 5'h12;
        wdata = 32'hdeadbeef;
        #2
        wen = 1'b1;
        waddr = 5'h13;
        wdata = 32'hbabecafe;
        #2
        wen = 1'b0;
        r1addr = 5'h12;
        r2addr = 5'h13;        
        #2
        wen = 1'b1;
        waddr = 5'h00;
        wdata = 32'hbbc0ffee;
        #2
        wen = 1'b1;
        waddr = 5'h01;
        wdata = 32'hefbeadde;
        #2
        wen = 1'b0;
        r1addr = 5'h00;
        r2addr = 5'h01;
        #2
        $finish;
    end


endmodule

RegFile.vcd
$date
	Thu Jun 13 12:18:11 2024
$end
$version
	Icarus Verilog
$end
$timescale
	1s
$end
$scope module RegFile_tb $end
$scope module DUT $end
$var wire 1 ! i_clk $end
$var wire 5 " i_r1addr [4:0] $end
$var wire 5 # i_r2addr [4:0] $end
$var wire 5 $ i_waddr [4:0] $end
$var wire 32 % i_wdata [31:0] $end
$var wire 1 & i_wen $end
$var wire 32 ' o_r1data [31:0] $end
$var wire 32 ( o_r2data [31:0] $end
$var reg 32 ) r1data [31:0] $end
$var reg 32 * r2data [31:0] $end
$upscope $end
$upscope $end
$enddefinitions $end
$comment Show the parameter values. $end
$dumpall
$end
#0
$dumpvars
bx *
bx )
bx (
bx '
0&
b0 %
b0 $
b0 #
b0 "
0!
$end
#1
b0 (
b0 *
b0 '
b0 )
1!
#2
0!
b11011110101011011011111011101111 %
b10010 $
1&
#3
1!
#4
0!
b10111010101111101100101011111110 %
b10011 $
#5
1!
#6
0!
b10011 #
b10010 "
0&
#7
b10111010101111101100101011111110 (
b10111010101111101100101011111110 *
b11011110101011011011111011101111 '
b11011110101011011011111011101111 )
1!
#8
0!
b10111011110000001111111111101110 %
b0 $
1&
#9
b0 (
b0 *
b0 '
b0 )
1!
#10
0!
b11101111101111101010110111011110 %
b1 $
#11
1!
#12
0!
b1 #
b0 "
0&
#13
b11101111101111101010110111011110 (
b11101111101111101010110111011110 *
1!
